{
	"version": "https://jsonfeed.org/version/1",
	"title": "Jarrod Whaley",
	"home_page_url": "http://www.jarrodwhaley.com/",
	"feed_url": "http://www.jarrodwhaley.com/feed.json",
	"items": [
		
		{
			"id": "http://jbwhaley.micro.blog/2017/12/13/doesnt-it-seem.html",
	      	
			"content_html": "<p>Doesn’t it seem like “<a href=\"https://www.nytimes.com/2017/12/12/us/politics/alabama-senate-election-moore.html\">confusion at the polls</a>” always benefits Republicans?</p>\n",
			"date_published": "2017-12-12T16:43:00-08:00",
			"url": "http://www.jarrodwhaley.com/2017/12/12/doesnt-it-seem.html"
		},
		
		{
			"id": "http://jbwhaley.micro.blog/2017/12/13/wired-published-a.html",
	      	
			"content_html": "<p><em>Wired</em> published a <a href=\"https://www.wired.com/story/how-email-open-tracking-quietly-took-over-the-web/\">great history of the practice of tracking when emails are opened</a>. As you might expect, many slimy tales are told.</p>\n",
			"date_published": "2017-12-12T16:37:00-08:00",
			"url": "http://www.jarrodwhaley.com/2017/12/12/wired-published-a.html"
		},
		
		{
			"id": "http://jbwhaley.micro.blog/2017/12/12/if-you-oppose.html",
	      	
			"content_html": "<p>If you oppose stupidity, take heart. Your opponent is stupid, after all.</p>\n",
			"date_published": "2017-12-12T00:56:00-08:00",
			"url": "http://www.jarrodwhaley.com/2017/12/12/if-you-oppose.html"
		},
		
		{
			"id": "http://jbwhaley.micro.blog/2017/12/12/life-is-rough.html",
	      	
			"content_html": "<p>Life is rough for her.</p>\n\n<p><img src=\"http://www.jarrodwhaley.com/uploads/2017/3624c62783.jpg\" width=\"600\" height=\"600\" /></p>\n",
			"date_published": "2017-12-12T00:41:00-08:00",
			"url": "http://www.jarrodwhaley.com/2017/12/12/life-is-rough.html"
		},
		
		{
			"id": "http://jbwhaley.micro.blog/2017/12/12/a-stolen-moment.html",
	      	
			"content_html": "<p>A stolen moment of peace beside the Pacific.</p>\n\n<p><img src=\"http://www.jarrodwhaley.com/uploads/2017/b079dcf128.jpg\" width=\"600\" height=\"600\" /></p>\n",
			"date_published": "2017-12-11T17:58:00-08:00",
			"url": "http://www.jarrodwhaley.com/2017/12/11/a-stolen-moment.html"
		},
		
		{
			"id": "http://jbwhaley.micro.blog/2017/12/11/the-toxic-nature.html",
	      	
			"content_html": "<p>The toxic nature of social media <a href=\"https://www.theverge.com/2017/12/11/16761016/former-facebook-exec-ripping-apart-society\">becomes more apparent by the day</a>. We are slowly poisoning our own minds and cultures.</p>\n",
			"date_published": "2017-12-11T09:34:00-08:00",
			"url": "http://www.jarrodwhaley.com/2017/12/11/the-toxic-nature.html"
		},
		
		{
			"id": "http://jbwhaley.micro.blog/2017/12/11/pai-is-determined.html",
	      	
			"content_html": "<p>Pai is determined to <a href=\"https://arstechnica.com/tech-policy/2017/12/fcc-chair-still-refuses-to-help-investigate-net-neutrality-comment-fraud/\">force the Net Neutrality repeal vote</a>, come Hell, high water, or an investigation carried out by the New York State Attorney General’s office.</p>\n",
			"date_published": "2017-12-11T09:21:00-08:00",
			"url": "http://www.jarrodwhaley.com/2017/12/11/pai-is-determined.html"
		},
		
		{
			"id": "http://jbwhaley.micro.blog/2017/12/11/should-you-say.html",
	      	
			"content_html": "<blockquote>\n  <p><a href=\"https://www.theverge.com/circuitbreaker/2017/12/10/16751232/smart-assistants-please-thank-you-politeness-manners-alexa-siri-google-cortana\">Should you say ‘please’ and ‘thank you’ to your Amazon Echo or Google Home?</a></p>\n</blockquote>\n\n<p>No, but you probably shouldn’t be saying anything to them <em>at all</em>.</p>\n",
			"date_published": "2017-12-10T16:36:00-08:00",
			"url": "http://www.jarrodwhaley.com/2017/12/10/should-you-say.html"
		},
		
		{
			"id": "http://jbwhaley.micro.blog/2017/12/10/well-this-is.html",
	      	
			"content_html": "<p>Well, <a href=\"https://www.blackhat.com/docs/eu-17/materials/eu-17-Arnaboldi-Exposing-Hidden-Exploitable-Behaviors-In-Programming-Languages-Using-Differential-Fuzzing-wp.pdf\">this is certainly disconcerting</a>. </p>\n",
			"date_published": "2017-12-10T11:55:00-08:00",
			"url": "http://www.jarrodwhaley.com/2017/12/10/well-this-is.html"
		},
		
		{
			"id": "http://jbwhaley.micro.blog/2017/12/10/didnt-learn-from.html",
	      	
			"content_html": "<p>Didn’t learn from the mistakes of Deceiver I, eh?</p>\n\n<p><img src=\"http://www.jarrodwhaley.com/uploads/2017/c84dfb06c0.jpg\" width=\"600\" height=\"600\" /></p>\n",
			"date_published": "2017-12-09T18:53:00-08:00",
			"url": "http://www.jarrodwhaley.com/2017/12/09/didnt-learn-from.html"
		}
		
	]
}
